structprop/__init__.py
structprop-0.0.11.dist-info/LICENSE
structprop-0.0.11.dist-info/METADATA
structprop-0.0.11.dist-info/WHEEL
structprop-0.0.11.dist-info/top_level.txt
structprop-0.0.11.dist-info/RECORD
