Metadata-Version: 2.1
Name: structprop
Version: 0.0.11
Summary: Parser for structured property config file format
Home-page: UNKNOWN
Author: Edgeware AB
Author-email: info@edgeware.tv
License: MIT
Platform: UNKNOWN
Classifier: Intended Audience :: Developers
Classifier: Topic :: Software Development
Requires-Dist: six
